dvoryan/__init__.py
dvoryan/dvoryan.py
dvoryan-0.0.3.data/scripts/dvoryan.py
dvoryan-0.0.3.dist-info/METADATA
dvoryan-0.0.3.dist-info/WHEEL
dvoryan-0.0.3.dist-info/license.txt
dvoryan-0.0.3.dist-info/top_level.txt
dvoryan-0.0.3.dist-info/RECORD
