Metadata-Version: 2.1
Name: dvoryan
Version: 0.0.3
Summary: Reproducible and efficient diffusion kurtosis imaging in Python.
Home-page: https://github.com/kerkelae/dkmri
Author: Leevi Kerkelä
Author-email: leevi.kerkela@protonmail.com
License: MIT
Platform: UNKNOWN
License-File: license.txt
Requires-Dist: jax
Requires-Dist: jaxlib
Requires-Dist: nibabel
Requires-Dist: numba
Requires-Dist: numpy
Requires-Dist: scikit-learn
